pivirt/__init__.py
pivirt/guestfish_utils.py
pivirt/logging_config.py
pivirt/qemu_utils.py
pivirt/utils.py
pivirt/vm_manager.py
pivirt_core-1.0.0.dist-info/LICENSE.txt
pivirt_core-1.0.0.dist-info/METADATA
pivirt_core-1.0.0.dist-info/WHEEL
pivirt_core-1.0.0.dist-info/top_level.txt
pivirt_core-1.0.0.dist-info/RECORD
