Metadata-Version: 2.1
Name: pivirt-core
Version: 1.0.0
Summary: A Python library to manage and test Raspberry Pi OS images with QEMU
Author-email: Federico Sauter <pivirt@pm.me>
License: GNU Lesser General Public License v3.0 or later (LGPL-3.0-or-later)
Project-URL: Documentation, https://github.com/federico-sauter/pivirt-core
Project-URL: Source, https://github.com/federico-sauter/pivirt-core
Project-URL: Contact, https://github.com/federico-sauter/pivirt-core
Keywords: raspberry-pi,rpi,qemu,virtualization,ci-cd,embedded-systems
Classifier: Programming Language :: Python :: 3
Classifier: License :: OSI Approved :: GNU Lesser General Public License v3 or later (LGPLv3+)
Classifier: Operating System :: OS Independent
License-File: LICENSE.txt
